Metadata-Version: 1.2
Name: libn
Version: 0.1.6
Summary: Python implementation of NANO-related functions.
Home-page: https://github.com/rbw/libn
Author: rbw
Author-email: rbw@vault13.org
License: MIT
Platform: UNKNOWN
Requires-Python: >=3.6
